Lab4/library.v
`timescale 1ns/1ps

// ALU Module. Inputs: inA, inB. Output: out. 
// Operations: bitwise and (op = 0)
//             bitwise or  (op = 1)
//             addition (op = 2)
//             subtraction (op = 6)
//             slt  (op = 7)
//             nor (op = 12)
module ALU (out, zero, inA, inB, op);
  parameter N = 32;
  output reg [N-1:0] out;
  output reg zero;
  input  [N-1:0] inA, inB;
  input    [3:0] op;

  always @* begin
    case (op)
      4'h0: out = inA & inB;
      4'h1: out = inA | inB;
      4'h2: out = inA + inB;
      4'h6: out = inA - inB;
      4'h7: out = (inA < inB) ? 1 : 0;
      4'hc: out = ~(inA | inB);
    endcase

    if (out == 0) zero = 1;
    else zero = 0;
  end
endmodule

// Register File Module. Read ports: address raA, data rdA
//                            address raB, data rdB
//                Write port: address wa, data wd, enable wen.
module RegFile (clock, reset, raA, raB, wa, wen, wd, rdA, rdB);
  input clock, reset, wen;
  input [4:0] raA, raB, wa;
  input [31:0] wd;
  output reg [31:0] rdA, rdB;
  output reg [31:0] data[31:0];

  always @(negedge clock, reset) begin
    if (reset) begin
      if (wen) data[wa] = wd;
    end
  end

  always @(data[raA], data[raB], raA, raB) begin
    rdA = data[raA];
    rdB = data[raB];
  end
endmodule

Lab4/testbench.v
// Define top-level testbench
// ~~~~~~~~~~~~~~~~~~~~~~~~~~~~~
// Top level has no inputs or outputs
// It only needs to instantiate CPU, Drive the inputs to CPU (clock, reset)
// and monitor the outputs. This is what all testbenches do

`timescale 1ns/1ps
`define clock_period 10

module cpu_tb;
reg       clock, reset;    // Clock and reset signals
reg   [4:0] raA, raB, wa;
reg         wen;
reg   [3:0] ALUop;
wire   [31:0] wd;
wire  [31:0] rdA, rdB; 
wire         ALUZero; 
integer i;

// Instantiate regfile module
RegFile regs(clock, reset, raA, raB, wa, wen, wd, rdA, rdB);
ALU alu(wd, ALUZero, rdA, rdB, ALUop);

initial begin  // Ta statements apo ayto to begin mexri to "end" einai seiriaka
      
  // Initialize the module 
   $dumpfile("dumpfile.vcd");
   $dumpvars(0, cpu_tb);
   clock = 1'b0;       
   reset = 1'b0;  // Apply reset for a few cycles
   #(4.25*`clock_period) reset = 1'b1;

   // Force initialization of the Register File
   for (i = 0; i < 32; i = i+1)
      regs.data[i] = i;   // Note that always R0 = 0 in MIPS 
      
   // Now apply some inputs. 
   // You SHOULD EXTEND this part of the code with extra inputs 
   #(`clock_period)
   ALUop = 4'h0; raA = 5'h1; raB = 5'h3; wa = 5'h3; wen = 1'b1; 
   #(`clock_period)
   ALUop = 4'h2; wa = 5'h4;
   #(`clock_period)
   ALUop = 4'h6; raA=5'h5; raB=5'h1; wa=5'h3;
   #(`clock_period)
   ALUop = 4'h7; raA=5'h3; raB=5'h2; wa=5'h1;
   #(`clock_period)
   ALUop = 4'hc; raA=5'h2; raB=5'h3; wa=5'h4;
   #(`clock_period)
   wen = 1'b0;

   $finish;
end 

// Generate clock by inverting the signal every half of clock period
always begin
   #(`clock_period/2) clock = ~clock;  
end
   
endmodule

Lab4/dumpfile.vcd
$date
	Tue Nov 28 17:00:24 2023
$end
$version
	Icarus Verilog
$end
$timescale
	1ps
$end
$scope module cpu_tb $end
$var wire 32 ! wd [31:0] $end
$var wire 32 " rdB [31:0] $end
$var wire 32 # rdA [31:0] $end
$var wire 1 $ ALUZero $end
$var reg 4 % ALUop [3:0] $end
$var reg 1 & clock $end
$var reg 5 ' raA [4:0] $end
$var reg 5 ( raB [4:0] $end
$var reg 1 ) reset $end
$var reg 5 * wa [4:0] $end
$var reg 1 + wen $end
$var integer 32 , i [31:0] $end
$scope module alu $end
$var wire 4 - op [3:0] $end
$var wire 32 . inB [31:0] $end
$var wire 32 / inA [31:0] $end
$var reg 32 0 out [31:0] $end
$var reg 1 $ zero $end
$upscope $end
$scope module regs $end
$var wire 1 & clock $end
$var wire 5 1 raA [4:0] $end
$var wire 5 2 raB [4:0] $end
$var wire 1 ) reset $end
$var wire 5 3 wa [4:0] $end
$var wire 32 4 wd [31:0] $end
$var wire 1 + wen $end
$var reg 32 5 rdA [31:0] $end
$var reg 32 6 rdB [31:0] $end
$upscope $end
$upscope $end
$enddefinitions $end
#0
$dumpvars
bx 6
bx 5
bx 4
bx 3
bx 2
bx 1
bx 0
bx /
bx .
bx -
bx ,
x+
bx *
0)
bx (
bx '
0&
bx %
x$
bx #
bx "
bx !
$end
#1000
1&
#2000
0&
#3000
1&
#4000
0&
#5000
1&
#6000
0&
#7000
1&
#8000
0&
#8500
b100000 ,
1)
#9000
1&
#10000
0&
#10500
b1 !
b1 0
b1 4
b11 "
b11 .
b11 6
b1 #
b1 /
b1 5
0$
1+
b11 *
b11 3
b11 (
b11 2
b1 '
b1 1
b0 %
b0 -
#11000
1&
#12000
b1 "
b1 .
b1 6
0&
#12500
b10 !
b10 0
b10 4
b100 *
b100 3
b10 %
b10 -
#13000
1&
#14000
0&
#14500
b101 #
b101 /
b101 5
0$
b100 !
b100 0
b100 4
b11 *
b11 3
b1 (
b1 2
b101 '
b101 1
b110 %
b110 -
#15000
1&
#16000
0&
#16500
b10 "
b10 .
b10 6
b100 #
b100 /
b100 5
1$
b0 !
b0 0
b0 4
b1 *
b1 3
b10 (
b10 2
b11 '
b11 1
b111 %
b111 -
#17000
1&
#18000
0&
#18500
b100 "
b100 .
b100 6
b10 #
b10 /
b10 5
0$
b11111111111111111111111111111001 !
b11111111111111111111111111111001 0
b11111111111111111111111111111001 4
b100 *
b100 3
b11 (
b11 2
b10 '
b10 1
b1100 %
b1100 -
#19000
1&
#20000
0&
#20500
0+
